botface/__init__.py
botface-0.0.1.dist-info/METADATA
botface-0.0.1.dist-info/WHEEL
botface-0.0.1.dist-info/top_level.txt
botface-0.0.1.dist-info/RECORD
